mplex/__init__.py
mplex/annotate.py
mplex/artist.py
mplex/axes.py
mplex/axes_collection.py
mplex/cm.py
mplex/colors.py
mplex/core.py
mplex/figure.py
mplex/grid.py
mplex/plot.py
mplex/style.py
mplex/text.py
mplex/transforms.py
mplex/utils.py
mplex/stylesheets/default.mplstyle
mplex-0.0.7.dist-info/METADATA
mplex-0.0.7.dist-info/WHEEL
mplex-0.0.7.dist-info/licenses/LICENSE
mplex-0.0.7.dist-info/RECORD
