Metadata-Version: 2.3
Name: mplex
Version: 0.0.7
Summary: A matplotlib extension
Project-URL: Homepage, https://github.com/tkclam/mplex
Author-email: Thomas Ka Chung Lam <thomas.lam@epfl.ch>
License-File: LICENSE
Classifier: License :: OSI Approved :: MIT License
Classifier: Operating System :: OS Independent
Classifier: Programming Language :: Python :: 3
Requires-Python: >=3.7
